antenna_lib/__init__.py
antenna_lib/antenna.py
antenna_lib/exceptions.py
antenna_lib/antenna_parameters/__init__.py
antenna_lib/antenna_parameters/polarization.py
antenna_lib/array_antennas/__init__.py
antenna_lib/array_antennas/array.py
antenna_lib/array_antennas/broadside.py
antenna_lib/array_antennas/factory.py
antenna_lib/array_antennas/hansen_woodyard.py
antenna_lib/array_antennas/nonuniform_af.py
antenna_lib/array_antennas/ordinary_endfire.py
antenna_lib/array_antennas/uniform_af.py
antenna_lib/single_antennas/__init__.py
antenna_lib/single_antennas/dipole.py
antenna_lib/single_antennas/isotropic.py
antenna_lib/single_antennas/loop.py
antenna_lib/single_antennas/single.py
antenna_lib/utils/__init__.py
antenna_lib/utils/decorators.py
antenna_lib-0.0.1a0.dist-info/LICENSE
antenna_lib-0.0.1a0.dist-info/METADATA
antenna_lib-0.0.1a0.dist-info/WHEEL
antenna_lib-0.0.1a0.dist-info/top_level.txt
antenna_lib-0.0.1a0.dist-info/RECORD
