Metadata-Version: 2.1
Name: antenna-lib
Version: 0.0.1a0
Summary: Librería para diseño y visualización de antenas y sus parámetros
Author-email: Sergio Del Carpio <sadelcarpioa@gmail.com>
Maintainer-email: Sergio Del Carpio <sadelcarpioa@gmail.com>
License: MIT License
Project-URL: Repository, https://github.com/sadelcarpio/antenna-lib
Keywords: antenna,design
Classifier: Development Status :: 3 - Alpha
Classifier: License :: OSI Approved :: MIT License
Classifier: Programming Language :: Python :: 3
Classifier: Programming Language :: Python :: 3.9
Classifier: Programming Language :: Python :: 3.10
Classifier: Programming Language :: Python :: 3.11
Requires-Python: >=3.9
License-File: LICENSE
Requires-Dist: scipy ~=1.11.2
Requires-Dist: matplotlib ~=3.7.2
Provides-Extra: dev
Requires-Dist: pytest ~=7.4.0 ; extra == 'dev'
Requires-Dist: coverage ~=7.3.0 ; extra == 'dev'
Requires-Dist: flake8 ~=6.1.0 ; extra == 'dev'
Requires-Dist: build ~=0.10.0 ; extra == 'dev'
Requires-Dist: twine ~=4.0.2 ; extra == 'dev'
